dunlin/__init__.py
dunlin/_strike_goldd_algo.py
dunlin/load.py
dunlin/strike_goldd.py
dunlin/comp/__init__.py
dunlin/comp/child.py
dunlin/comp/flatten.py
dunlin/comp/flattenmodel.py
dunlin/comp/ode.py
dunlin/datastructures/__init__.py
dunlin/datastructures/bases.py
dunlin/datastructures/boundarycondition.py
dunlin/datastructures/coordinatecomponent.py
dunlin/datastructures/domain.py
dunlin/datastructures/domaintype.py
dunlin/datastructures/event.py
dunlin/datastructures/exception.py
dunlin/datastructures/function.py
dunlin/datastructures/geometrydefinition.py
dunlin/datastructures/gridconfig.py
dunlin/datastructures/masstransfer.py
dunlin/datastructures/modeldata.py
dunlin/datastructures/ode.py
dunlin/datastructures/rate.py
dunlin/datastructures/reaction.py
dunlin/datastructures/spatial.py
dunlin/datastructures/stateparam.py
dunlin/datastructures/unit.py
dunlin/datastructures/variable.py
dunlin/ode/__init__.py
dunlin/ode/basemodel.py
dunlin/ode/event.py
dunlin/ode/extrafunc.py
dunlin/ode/ivp.py
dunlin/ode/ode_coder.py
dunlin/ode/odemodel.py
dunlin/ode/odemodel_backup.py
dunlin/optimize/__init__.py
dunlin/optimize/algos.py
dunlin/optimize/curvefit.py
dunlin/optimize/curvefit_backup.py
dunlin/optimize/oed.py
dunlin/optimize/optimizer.py
dunlin/optimize/params.py
dunlin/optimize/readdata.py
dunlin/optimize/sensitivity.py
dunlin/optimize/trace.py
dunlin/optimize/wrap_SSE.py
dunlin/standardfile/__init__.py
dunlin/standardfile/dunl/__init__.py
dunlin/standardfile/dunl/builder.py
dunlin/standardfile/dunl/commonsequence.py
dunlin/standardfile/dunl/delim.py
dunlin/standardfile/dunl/parsepath.py
dunlin/standardfile/dunl/readdunl.py
dunlin/standardfile/dunl/readelement.py
dunlin/standardfile/dunl/readprimitive.py
dunlin/standardfile/dunl/readshorthand.py
dunlin/standardfile/dunl/readstring.py
dunlin/standardfile/dunl/writecode.py
dunlin/standardfile/dunl/writecustom.py
dunlin/standardfile/dunl/writeelement.py
dunlin/standardfile/dunl/writefile.py
dunlin/utils/__init__.py
dunlin-0.0.3.dist-info/LICENSE
dunlin-0.0.3.dist-info/LICENSE.rst
dunlin-0.0.3.dist-info/METADATA
dunlin-0.0.3.dist-info/WHEEL
dunlin-0.0.3.dist-info/top_level.txt
dunlin-0.0.3.dist-info/RECORD
